tyba_client/__init__.py
tyba_client/client.py
tyba_client/forecast.py
tyba_client/operations.py
tyba_client/utils.py
tyba_client-0.5.4.dist-info/METADATA
tyba_client-0.5.4.dist-info/WHEEL
tyba_client-0.5.4.dist-info/licenses/LICENSE
tyba_client-0.5.4.dist-info/RECORD
