Metadata-Version: 2.4
Name: tyba-client
Version: 0.5.4
Summary: A Python API client for the Tyba Public API
License-Expression: MIT
License-File: LICENSE
Author: Tyler Nisonoff
Author-email: tyler@tybaenergy.com
Requires-Python: >=3.10,<4.0
Classifier: Programming Language :: Python :: 3
Classifier: Programming Language :: Python :: 3.10
Classifier: Programming Language :: Python :: 3.11
Classifier: Programming Language :: Python :: 3.12
Classifier: Programming Language :: Python :: 3.13
Classifier: Programming Language :: Python :: 3.14
Requires-Dist: generation-models (>=0.10.8,<1.0.0)
Requires-Dist: pandas (>=2.3.2,<3.0.0)
Requires-Dist: requests (>=2.32.5,<3.0.0)
Requires-Dist: structlog (>=25.4.0,<26.0.0)
